train_unet/_init__.py
train_unet/main.py
train_unet/metrics.py
train_unet/plots.py
train_unet/reports.py
train_unet/versions.py
train_unet/model/_init__.py
train_unet/model/unet.py
train_unet/predict/_init__.py
train_unet/predict/predict.py
train_unet-0.0.2.dist-info/LICENSE
train_unet-0.0.2.dist-info/METADATA
train_unet-0.0.2.dist-info/WHEEL
train_unet-0.0.2.dist-info/top_level.txt
train_unet-0.0.2.dist-info/RECORD
