Metadata-Version: 2.1
Name: train-unet
Version: 0.0.2
Summary: To use U-net architecture and train models for medical imaging at ease.
Home-page: https://github.com/iamlmn/train-unet
Author: Lakshmi Naarayanan
Author-email: lakshminaarayananvs@rediffmail.com
License: UNKNOWN
Platform: UNKNOWN
Classifier: License :: OSI Approved :: MIT License
Classifier: Programming Language :: Python :: 3
Classifier: Programming Language :: Python :: 3.7
Requires-Python: >=3.6
Requires-Dist: numpy
Requires-Dist: keras (==2.2.4)
Requires-Dist: tensorflow (==1.13.1)
Requires-Dist: scipy
Requires-Dist: pandas
Requires-Dist: scikit-image
Requires-Dist: docopt
Requires-Dist: tqdm
